easysocks5/__init__.py
easysocks5/remote.py
easysocks5/server.py
easysocks5/socks5.py
easysocks5-0.0.5.dist-info/LICENSE
easysocks5-0.0.5.dist-info/METADATA
easysocks5-0.0.5.dist-info/WHEEL
easysocks5-0.0.5.dist-info/top_level.txt
easysocks5-0.0.5.dist-info/RECORD
