Metadata-Version: 2.1
Name: easysocks5
Version: 0.0.5
Summary: easysocks5 is a simple SOCKS5 server implementation with AsyncIO
Home-page: https://github.com/frankurcrazy/easysocks5
Author: Frank Chang
Author-email: frank@csie.io
License: MIT
Keywords: socks,socks5,asyncio
Platform: UNKNOWN
Classifier: License :: OSI Approved :: MIT License
Classifier: Programming Language :: Python :: 3
Classifier: Programming Language :: Python :: 3.7
Classifier: License :: OSI Approved :: MIT License
Classifier: Operating System :: OS Independent
Classifier: Topic :: Internet
Classifier: Topic :: System :: Networking
Requires-Python: >=3.7
